{
  "conditions": [
    {
      "timestamp": "2026-05-20T03:48:00.000Z",
      "source": "aws+metoffice",
      "snow": {
        "summit": {
          "base": 0,
          "fresh_1h": 0,
          "fresh_24h": 0
        },
        "mid": {
          "base": 0,
          "fresh_1h": 0,
          "fresh_24h": 0
        },
        "base": {
          "base": 0,
          "fresh_1h": 0,
          "fresh_24h": 0
        }
      },
      "weather": {
        "summit": {
          "temp_c": 4.439,
          "wind_kmh": 8.9,
          "wind_dir": "WSW",
          "precip_mm": 0,
          "weatherCode": 1
        },
        "mid": {
          "temp_c": 7.4615,
          "wind_kmh": 8,
          "wind_dir": "WSW",
          "precip_mm": 0,
          "weatherCode": 1
        },
        "base": {
          "temp_c": 8.339,
          "wind_kmh": 6.2,
          "wind_dir": "WSW",
          "precip_mm": 0,
          "weatherCode": 1
        }
      }
    },
    {
      "timestamp": "2026-05-20T07:48:00.000Z",
      "source": "aws+metoffice",
      "snow": {
        "summit": {
          "base": 0,
          "fresh_1h": 0,
          "fresh_24h": 0
        },
        "mid": {
          "base": 0,
          "fresh_1h": 0,
          "fresh_24h": 0
        },
        "base": {
          "base": 0,
          "fresh_1h": 0,
          "fresh_24h": 0
        }
      },
      "weather": {
        "summit": {
          "temp_c": 4.9315,
          "wind_kmh": 15.4,
          "wind_dir": "W",
          "precip_mm": 0,
          "weatherCode": 1
        },
        "mid": {
          "temp_c": 7.954,
          "wind_kmh": 13.9,
          "wind_dir": "W",
          "precip_mm": 0,
          "weatherCode": 1
        },
        "base": {
          "temp_c": 8.8315,
          "wind_kmh": 10.8,
          "wind_dir": "W",
          "precip_mm": 0,
          "weatherCode": 1
        }
      }
    },
    {
      "timestamp": "2026-05-20T17:48:00.000Z",
      "source": "aws+metoffice",
      "snow": {
        "summit": {
          "base": 0,
          "fresh_1h": 0,
          "fresh_24h": 0
        },
        "mid": {
          "base": 0,
          "fresh_1h": 0,
          "fresh_24h": 0
        },
        "base": {
          "base": 0,
          "fresh_1h": 0,
          "fresh_24h": 0
        }
      },
      "weather": {
        "summit": {
          "temp_c": 4.0009999999999994,
          "wind_kmh": 21.4,
          "wind_dir": "W",
          "precip_mm": 0,
          "weatherCode": 1
        },
        "mid": {
          "temp_c": 7.023499999999999,
          "wind_kmh": 19.3,
          "wind_dir": "W",
          "precip_mm": 0,
          "weatherCode": 1
        },
        "base": {
          "temp_c": 7.901,
          "wind_kmh": 15,
          "wind_dir": "W",
          "precip_mm": 0,
          "weatherCode": 1
        }
      }
    },
    {
      "timestamp": "2026-05-20T20:48:00.000Z",
      "source": "aws+metoffice",
      "snow": {
        "summit": {
          "base": 0,
          "fresh_1h": 0,
          "fresh_24h": 0
        },
        "mid": {
          "base": 0,
          "fresh_1h": 0,
          "fresh_24h": 0
        },
        "base": {
          "base": 0,
          "fresh_1h": 0,
          "fresh_24h": 0
        }
      },
      "weather": {
        "summit": {
          "temp_c": 2.2835,
          "wind_kmh": 25.7,
          "wind_dir": "W",
          "precip_mm": 0,
          "weatherCode": 1
        },
        "mid": {
          "temp_c": 5.306,
          "wind_kmh": 23.1,
          "wind_dir": "W",
          "precip_mm": 0,
          "weatherCode": 1
        },
        "base": {
          "temp_c": 6.1835,
          "wind_kmh": 18,
          "wind_dir": "W",
          "precip_mm": 0,
          "weatherCode": 1
        }
      }
    },
    {
      "timestamp": "2026-05-20T21:48:00.000Z",
      "source": "aws+metoffice",
      "snow": {
        "summit": {
          "base": 0,
          "fresh_1h": 0,
          "fresh_24h": 0
        },
        "mid": {
          "base": 0,
          "fresh_1h": 0,
          "fresh_24h": 0
        },
        "base": {
          "base": 0,
          "fresh_1h": 0,
          "fresh_24h": 0
        }
      },
      "weather": {
        "summit": {
          "temp_c": 1.675,
          "wind_kmh": 23.2,
          "wind_dir": "W",
          "precip_mm": 0,
          "weatherCode": 1
        },
        "mid": {
          "temp_c": 4.6975,
          "wind_kmh": 20.9,
          "wind_dir": "W",
          "precip_mm": 0,
          "weatherCode": 1
        },
        "base": {
          "temp_c": 5.575,
          "wind_kmh": 16.2,
          "wind_dir": "W",
          "precip_mm": 0,
          "weatherCode": 1
        }
      }
    },
    {
      "timestamp": "2026-05-21T00:48:00.000Z",
      "source": "aws+metoffice",
      "snow": {
        "summit": {
          "base": 0,
          "fresh_1h": 0,
          "fresh_24h": 0
        },
        "mid": {
          "base": 0,
          "fresh_1h": 0,
          "fresh_24h": 0
        },
        "base": {
          "base": 0,
          "fresh_1h": 0,
          "fresh_24h": 0
        }
      },
      "weather": {
        "summit": {
          "temp_c": 3.659,
          "wind_kmh": 30.4,
          "wind_dir": "W",
          "precip_mm": 0,
          "weatherCode": 1
        },
        "mid": {
          "temp_c": 6.6815,
          "wind_kmh": 27.4,
          "wind_dir": "W",
          "precip_mm": 0,
          "weatherCode": 1
        },
        "base": {
          "temp_c": 7.558999999999999,
          "wind_kmh": 21.3,
          "wind_dir": "W",
          "precip_mm": 0,
          "weatherCode": 1
        }
      }
    }
  ]
}